nhandu/__init__.py
nhandu/__main__.py
nhandu/executor.py
nhandu/models.py
nhandu/parser.py
nhandu/py.typed
nhandu/renderer.py
nhandu/converters/__init__.py
nhandu/converters/notebook.py
nhandu-0.3.1.dist-info/licenses/LICENSE
nhandu-0.3.1.dist-info/METADATA
nhandu-0.3.1.dist-info/WHEEL
nhandu-0.3.1.dist-info/entry_points.txt
nhandu-0.3.1.dist-info/top_level.txt
nhandu-0.3.1.dist-info/RECORD
