Metadata-Version: 2.4
Name: nhandu
Version: 0.3.1
Summary: A literate programming tool for Python that weaves code and documentation into scientific reports
Author-email: Tiago Tresoldi <tiago.tresoldi@lingfil.uu.se>
License-Expression: MIT
Project-URL: Homepage, https://github.com/tresoldi/nhandu
Project-URL: Issues, https://github.com/tresoldi/nhandu/issues
Keywords: literate-programming,scientific-computing,reports,documentation
Classifier: Development Status :: 3 - Alpha
Classifier: Intended Audience :: Science/Research
Classifier: Programming Language :: Python :: 3
Classifier: Programming Language :: Python :: 3.10
Classifier: Programming Language :: Python :: 3.11
Classifier: Programming Language :: Python :: 3.12
Classifier: Topic :: Documentation
Classifier: Topic :: Scientific/Engineering
Requires-Python: >=3.10
License-File: LICENSE
Requires-Dist: pyyaml>=6.0
Requires-Dist: mistune>=3.0
Requires-Dist: pygments>=2.19
Provides-Extra: dev
Requires-Dist: pytest>=7.0; extra == "dev"
Requires-Dist: pytest-cov>=4.0; extra == "dev"
Requires-Dist: mypy>=1.0; extra == "dev"
Requires-Dist: ruff>=0.1.0; extra == "dev"
Requires-Dist: types-PyYAML; extra == "dev"
Requires-Dist: types-Pygments; extra == "dev"
Requires-Dist: build>=1.0; extra == "dev"
Requires-Dist: twine>=4.0; extra == "dev"
Provides-Extra: test
Requires-Dist: numpy>=1.20; extra == "test"
Requires-Dist: pandas>=2.0; extra == "test"
Requires-Dist: matplotlib>=3.5; extra == "test"
Provides-Extra: jupyter
Requires-Dist: nbformat>=5.0; extra == "jupyter"
Requires-Dist: pyyaml>=6.0; extra == "jupyter"
Provides-Extra: all
Requires-Dist: nhandu[dev,jupyter,test]; extra == "all"
Dynamic: license-file
